wasspost/__init__.py
wasspost/__main__.py
wasspost/geometry.py
wasspost/plotting.py
wasspost/spectra.py
wasspost/wasspost.py
wasspost-0.4.2.dist-info/METADATA
wasspost-0.4.2.dist-info/WHEEL
wasspost-0.4.2.dist-info/entry_points.txt
wasspost-0.4.2.dist-info/top_level.txt
wasspost-0.4.2.dist-info/RECORD
