Metadata-Version: 2.4
Name: wasspost
Version: 0.4.2
Summary: WASS post processing tool
Author: Filippo Bergamasco
Author-email: filippo.bergamasco@unive.it
License: GPL3
Project-URL: homepage, https://sites.google.com/unive.it/wass
Project-URL: repository, https://github.com/fbergama/wass/tree/master/postproc
Keywords: WASS,3D,Post processing
Classifier: Programming Language :: Python :: 3
Classifier: Development Status :: 4 - Beta
Requires-Python: >=3.9
Requires-Dist: matplotlib
Requires-Dist: colorama
Requires-Dist: scipy
Requires-Dist: numpy
Requires-Dist: tqdm
Requires-Dist: opencv-python>=2.4.6
Requires-Dist: netcdf4
